fragmap/__init__.py
fragmap/commitdiff.py
fragmap/common_ui.py
fragmap/console_color.py
fragmap/console_ui.py
fragmap/datastructure_util.py
fragmap/debug.py
fragmap/enumerate_paths.py
fragmap/file_selection.py
fragmap/generate_matrix.py
fragmap/graph.py
fragmap/httphelper.py
fragmap/list_dict.py
fragmap/load_commits.py
fragmap/main.py
fragmap/span.py
fragmap/spg.py
fragmap/stable_list_dict.py
fragmap/update.py
fragmap/web_ui.py
getch/__init__.py
getch/getch.py
tests/infrastructure.py
tests/native_git.py
tests/test_connection.py
tests/test_general.py
tests/test_graph_add_and_propagate.py
tests/test_moved_span.py
tests/test_span.py
tests/test_system.py
tests/update_tests.py
fragmap-0.4.4.dist-info/LICENSE
fragmap-0.4.4.dist-info/METADATA
fragmap-0.4.4.dist-info/WHEEL
fragmap-0.4.4.dist-info/entry_points.txt
fragmap-0.4.4.dist-info/pbr.json
fragmap-0.4.4.dist-info/top_level.txt
fragmap-0.4.4.dist-info/RECORD
