Metadata-Version: 2.1
Name: fragmap
Version: 0.4.4
Summary: Visualize a timeline of Git commit changes on a grid
Home-page: https://github.com/amollberg/fragmap
Author: Alexander Mollberg
Author-email: amollberg@users.noreply.github.com
License: BSD
Keywords: git visualization console terminal
Classifier: Programming Language :: Python :: 3
Classifier: Topic :: Software Development :: Version Control
Classifier: Environment :: Console
Classifier: Topic :: Utilities
Classifier: License :: OSI Approved :: BSD License
Requires-Python: >=3.7
License-File: LICENSE
Requires-Dist: backports.shutil-get-terminal-size>=1.0.0
Requires-Dist: pygit2>=0.28.1
Requires-Dist: yattag==1.10.0
